AnkiVim-1.5.3.data/scripts/anki-vim
AnkiVim-1.5.3.dist-info/METADATA
AnkiVim-1.5.3.dist-info/RECORD
AnkiVim-1.5.3.dist-info/WHEEL
AnkiVim-1.5.3.dist-info/top_level.txt
ankivim/__init__.py
ankivim/cards.py
ankivim/errors.py
ankivim/UltiSnips/anki_vim.snippets
ankivim/tests/__init__.py
ankivim/tests/test_cards.py
