Metadata-Version: 2.1
Name: AnkiVim
Version: 1.5.3
Summary: Use vim to rapidly write textfiles immediately importable into anki(1).
Home-page: https://github.com/MFreidank/VimForAnki
Author: Moritz Freidank
Author-email: freidankm@yahoo.de
Maintainer: Moritz Freidank
Maintainer-email: freidankm@yahoo.de
License: MIT
Download-URL: https://github.com/MFreidank/VimForAnki/tarball/1.5.3
Platform: UNKNOWN
